CHANGES.txt
MANIFEST.in
README.rst
setup.py
docs/LICENSE.GPL
docs/LICENSE.txt
wildcard/__init__.py
wildcard.fixmissing.egg-info/PKG-INFO
wildcard.fixmissing.egg-info/SOURCES.txt
wildcard.fixmissing.egg-info/dependency_links.txt
wildcard.fixmissing.egg-info/entry_points.txt
wildcard.fixmissing.egg-info/namespace_packages.txt
wildcard.fixmissing.egg-info/not-zip-safe
wildcard.fixmissing.egg-info/requires.txt
wildcard.fixmissing.egg-info/top_level.txt
wildcard/fixmissing/__init__.py
wildcard/fixmissing/configure.zcml
wildcard/fixmissing/interfaces.py
wildcard/fixmissing/objects.py