Metadata-Version: 1.1
Name: wildcard.fixmissing
Version: 1.0
Summary: a package that allows you to fix missing modules which cause errors with the ZODB
Home-page: https://github.com/collective/wildcard.fixmissing/
Author: Nathan Van Gheem
Author-email: nathan.vangheem@wildcardcorp.com
License: GPL
Platform: UNKNOWN
Classifier: Framework :: Plone
Classifier: Programming Language :: Python
